Metadata-Version: 1.0
Name: distributions-chams
Version: 0.1
Summary: Gaussian distributions_chams
Home-page: UNKNOWN
Author: Chams Rutkowski
Author-email: chams.rut@gmail.com
License: UNKNOWN
Platform: UNKNOWN
